{
  "type": "GROUP",
"name": "Global Information",
"path": "",
"pathFormatted": "group_missing-name-b06d1",
"stats": {
    "name": "Global Information",
    "numberOfRequests": {
        "total": 24,
        "ok": 20,
        "ko": 4
    },
    "minResponseTime": {
        "total": 248,
        "ok": 248,
        "ko": 757
    },
    "maxResponseTime": {
        "total": 1838,
        "ok": 1256,
        "ko": 1838
    },
    "meanResponseTime": {
        "total": 779,
        "ok": 710,
        "ko": 1124
    },
    "standardDeviation": {
        "total": 358,
        "ok": 299,
        "ko": 421
    },
    "percentiles1": {
        "total": 758,
        "ok": 747,
        "ko": 950
    },
    "percentiles2": {
        "total": 993,
        "ok": 945,
        "ko": 1200
    },
    "percentiles3": {
        "total": 1224,
        "ok": 1057,
        "ko": 1710
    },
    "percentiles4": {
        "total": 1704,
        "ok": 1216,
        "ko": 1812
    },
    "group1": {
    "name": "t < 800 ms",
    "count": 12,
    "percentage": 50
},
    "group2": {
    "name": "800 ms < t < 1200 ms",
    "count": 7,
    "percentage": 29
},
    "group3": {
    "name": "t > 1200 ms",
    "count": 1,
    "percentage": 4
},
    "group4": {
    "name": "failed",
    "count": 4,
    "percentage": 17
},
    "meanNumberOfRequestsPerSecond": {
        "total": 3.0,
        "ok": 2.5,
        "ko": 0.5
    }
},
"contents": {
"group_petstore-s01-pe-51a38": {
          "type": "GROUP",
"name": "PetStore_S01_PetSearch_101_LaunchURL",
"path": "PetStore_S01_PetSearch_101_LaunchURL",
"pathFormatted": "group_petstore-s01-pe-51a38",
"stats": {
    "name": "PetStore_S01_PetSearch_101_LaunchURL",
    "numberOfRequests": {
        "total": 1,
        "ok": 0,
        "ko": 1
    },
    "minResponseTime": {
        "total": 3419,
        "ok": 0,
        "ko": 3419
    },
    "maxResponseTime": {
        "total": 3419,
        "ok": 0,
        "ko": 3419
    },
    "meanResponseTime": {
        "total": 3419,
        "ok": 0,
        "ko": 3419
    },
    "standardDeviation": {
        "total": 0,
        "ok": 0,
        "ko": 0
    },
    "percentiles1": {
        "total": 3419,
        "ok": 0,
        "ko": 3419
    },
    "percentiles2": {
        "total": 3419,
        "ok": 0,
        "ko": 3419
    },
    "percentiles3": {
        "total": 3419,
        "ok": 0,
        "ko": 3419
    },
    "percentiles4": {
        "total": 3419,
        "ok": 0,
        "ko": 3419
    },
    "group1": {
    "name": "t < 800 ms",
    "count": 0,
    "percentage": 0
},
    "group2": {
    "name": "800 ms < t < 1200 ms",
    "count": 0,
    "percentage": 0
},
    "group3": {
    "name": "t > 1200 ms",
    "count": 0,
    "percentage": 0
},
    "group4": {
    "name": "failed",
    "count": 1,
    "percentage": 100
},
    "meanNumberOfRequestsPerSecond": {
        "total": 0.125,
        "ok": 0,
        "ko": 0.125
    }
},
"contents": {
"req_request-0-684d2": {
        "type": "REQUEST",
        "name": "request_0",
"path": "PetStore_S01_PetSearch_101_LaunchURL / request_0",
"pathFormatted": "req_petstore-s01-pe-36627",
"stats": {
    "name": "request_0",
    "numberOfRequests": {
        "total": 1,
        "ok": 0,
        "ko": 1
    },
    "minResponseTime": {
        "total": 1838,
        "ok": 0,
        "ko": 1838
    },
    "maxResponseTime": {
        "total": 1838,
        "ok": 0,
        "ko": 1838
    },
    "meanResponseTime": {
        "total": 1838,
        "ok": 0,
        "ko": 1838
    },
    "standardDeviation": {
        "total": 0,
        "ok": 0,
        "ko": 0
    },
    "percentiles1": {
        "total": 1838,
        "ok": 0,
        "ko": 1838
    },
    "percentiles2": {
        "total": 1838,
        "ok": 0,
        "ko": 1838
    },
    "percentiles3": {
        "total": 1838,
        "ok": 0,
        "ko": 1838
    },
    "percentiles4": {
        "total": 1838,
        "ok": 0,
        "ko": 1838
    },
    "group1": {
    "name": "t < 800 ms",
    "count": 0,
    "percentage": 0
},
    "group2": {
    "name": "800 ms < t < 1200 ms",
    "count": 0,
    "percentage": 0
},
    "group3": {
    "name": "t > 1200 ms",
    "count": 0,
    "percentage": 0
},
    "group4": {
    "name": "failed",
    "count": 1,
    "percentage": 100
},
    "meanNumberOfRequestsPerSecond": {
        "total": 0.125,
        "ok": 0,
        "ko": 0.125
    }
}
    },"req_request-1-46da4": {
        "type": "REQUEST",
        "name": "request_1",
"path": "PetStore_S01_PetSearch_101_LaunchURL / request_1",
"pathFormatted": "req_petstore-s01-pe-72317",
"stats": {
    "name": "request_1",
    "numberOfRequests": {
        "total": 1,
        "ok": 1,
        "ko": 0
    },
    "minResponseTime": {
        "total": 291,
        "ok": 291,
        "ko": 0
    },
    "maxResponseTime": {
        "total": 291,
        "ok": 291,
        "ko": 0
    },
    "meanResponseTime": {
        "total": 291,
        "ok": 291,
        "ko": 0
    },
    "standardDeviation": {
        "total": 0,
        "ok": 0,
        "ko": 0
    },
    "percentiles1": {
        "total": 291,
        "ok": 291,
        "ko": 0
    },
    "percentiles2": {
        "total": 291,
        "ok": 291,
        "ko": 0
    },
    "percentiles3": {
        "total": 291,
        "ok": 291,
        "ko": 0
    },
    "percentiles4": {
        "total": 291,
        "ok": 291,
        "ko": 0
    },
    "group1": {
    "name": "t < 800 ms",
    "count": 1,
    "percentage": 100
},
    "group2": {
    "name": "800 ms < t < 1200 ms",
    "count": 0,
    "percentage": 0
},
    "group3": {
    "name": "t > 1200 ms",
    "count": 0,
    "percentage": 0
},
    "group4": {
    "name": "failed",
    "count": 0,
    "percentage": 0
},
    "meanNumberOfRequestsPerSecond": {
        "total": 0.125,
        "ok": 0.125,
        "ko": 0
    }
}
    },"req_request-5-48829": {
        "type": "REQUEST",
        "name": "request_5",
"path": "PetStore_S01_PetSearch_101_LaunchURL / request_5",
"pathFormatted": "req_petstore-s01-pe-4e420",
"stats": {
    "name": "request_5",
    "numberOfRequests": {
        "total": 1,
        "ok": 1,
        "ko": 0
    },
    "minResponseTime": {
        "total": 721,
        "ok": 721,
        "ko": 0
    },
    "maxResponseTime": {
        "total": 721,
        "ok": 721,
        "ko": 0
    },
    "meanResponseTime": {
        "total": 721,
        "ok": 721,
        "ko": 0
    },
    "standardDeviation": {
        "total": 0,
        "ok": 0,
        "ko": 0
    },
    "percentiles1": {
        "total": 721,
        "ok": 721,
        "ko": 0
    },
    "percentiles2": {
        "total": 721,
        "ok": 721,
        "ko": 0
    },
    "percentiles3": {
        "total": 721,
        "ok": 721,
        "ko": 0
    },
    "percentiles4": {
        "total": 721,
        "ok": 721,
        "ko": 0
    },
    "group1": {
    "name": "t < 800 ms",
    "count": 1,
    "percentage": 100
},
    "group2": {
    "name": "800 ms < t < 1200 ms",
    "count": 0,
    "percentage": 0
},
    "group3": {
    "name": "t > 1200 ms",
    "count": 0,
    "percentage": 0
},
    "group4": {
    "name": "failed",
    "count": 0,
    "percentage": 0
},
    "meanNumberOfRequestsPerSecond": {
        "total": 0.125,
        "ok": 0.125,
        "ko": 0
    }
}
    },"req_request-13-5cca6": {
        "type": "REQUEST",
        "name": "request_13",
"path": "PetStore_S01_PetSearch_101_LaunchURL / request_13",
"pathFormatted": "req_petstore-s01-pe-efa45",
"stats": {
    "name": "request_13",
    "numberOfRequests": {
        "total": 1,
        "ok": 1,
        "ko": 0
    },
    "minResponseTime": {
        "total": 527,
        "ok": 527,
        "ko": 0
    },
    "maxResponseTime": {
        "total": 527,
        "ok": 527,
        "ko": 0
    },
    "meanResponseTime": {
        "total": 527,
        "ok": 527,
        "ko": 0
    },
    "standardDeviation": {
        "total": 0,
        "ok": 0,
        "ko": 0
    },
    "percentiles1": {
        "total": 527,
        "ok": 527,
        "ko": 0
    },
    "percentiles2": {
        "total": 527,
        "ok": 527,
        "ko": 0
    },
    "percentiles3": {
        "total": 527,
        "ok": 527,
        "ko": 0
    },
    "percentiles4": {
        "total": 527,
        "ok": 527,
        "ko": 0
    },
    "group1": {
    "name": "t < 800 ms",
    "count": 1,
    "percentage": 100
},
    "group2": {
    "name": "800 ms < t < 1200 ms",
    "count": 0,
    "percentage": 0
},
    "group3": {
    "name": "t > 1200 ms",
    "count": 0,
    "percentage": 0
},
    "group4": {
    "name": "failed",
    "count": 0,
    "percentage": 0
},
    "meanNumberOfRequestsPerSecond": {
        "total": 0.125,
        "ok": 0.125,
        "ko": 0
    }
}
    },"req_request-6-027a9": {
        "type": "REQUEST",
        "name": "request_6",
"path": "PetStore_S01_PetSearch_101_LaunchURL / request_6",
"pathFormatted": "req_petstore-s01-pe-1c67c",
"stats": {
    "name": "request_6",
    "numberOfRequests": {
        "total": 1,
        "ok": 1,
        "ko": 0
    },
    "minResponseTime": {
        "total": 872,
        "ok": 872,
        "ko": 0
    },
    "maxResponseTime": {
        "total": 872,
        "ok": 872,
        "ko": 0
    },
    "meanResponseTime": {
        "total": 872,
        "ok": 872,
        "ko": 0
    },
    "standardDeviation": {
        "total": 0,
        "ok": 0,
        "ko": 0
    },
    "percentiles1": {
        "total": 872,
        "ok": 872,
        "ko": 0
    },
    "percentiles2": {
        "total": 872,
        "ok": 872,
        "ko": 0
    },
    "percentiles3": {
        "total": 872,
        "ok": 872,
        "ko": 0
    },
    "percentiles4": {
        "total": 872,
        "ok": 872,
        "ko": 0
    },
    "group1": {
    "name": "t < 800 ms",
    "count": 0,
    "percentage": 0
},
    "group2": {
    "name": "800 ms < t < 1200 ms",
    "count": 1,
    "percentage": 100
},
    "group3": {
    "name": "t > 1200 ms",
    "count": 0,
    "percentage": 0
},
    "group4": {
    "name": "failed",
    "count": 0,
    "percentage": 0
},
    "meanNumberOfRequestsPerSecond": {
        "total": 0.125,
        "ok": 0.125,
        "ko": 0
    }
}
    },"req_request-10-1cfbe": {
        "type": "REQUEST",
        "name": "request_10",
"path": "PetStore_S01_PetSearch_101_LaunchURL / request_10",
"pathFormatted": "req_petstore-s01-pe-9044b",
"stats": {
    "name": "request_10",
    "numberOfRequests": {
        "total": 1,
        "ok": 1,
        "ko": 0
    },
    "minResponseTime": {
        "total": 1046,
        "ok": 1046,
        "ko": 0
    },
    "maxResponseTime": {
        "total": 1046,
        "ok": 1046,
        "ko": 0
    },
    "meanResponseTime": {
        "total": 1046,
        "ok": 1046,
        "ko": 0
    },
    "standardDeviation": {
        "total": 0,
        "ok": 0,
        "ko": 0
    },
    "percentiles1": {
        "total": 1046,
        "ok": 1046,
        "ko": 0
    },
    "percentiles2": {
        "total": 1046,
        "ok": 1046,
        "ko": 0
    },
    "percentiles3": {
        "total": 1046,
        "ok": 1046,
        "ko": 0
    },
    "percentiles4": {
        "total": 1046,
        "ok": 1046,
        "ko": 0
    },
    "group1": {
    "name": "t < 800 ms",
    "count": 0,
    "percentage": 0
},
    "group2": {
    "name": "800 ms < t < 1200 ms",
    "count": 1,
    "percentage": 100
},
    "group3": {
    "name": "t > 1200 ms",
    "count": 0,
    "percentage": 0
},
    "group4": {
    "name": "failed",
    "count": 0,
    "percentage": 0
},
    "meanNumberOfRequestsPerSecond": {
        "total": 0.125,
        "ok": 0.125,
        "ko": 0
    }
}
    },"req_request-9-d127e": {
        "type": "REQUEST",
        "name": "request_9",
"path": "PetStore_S01_PetSearch_101_LaunchURL / request_9",
"pathFormatted": "req_petstore-s01-pe-01704",
"stats": {
    "name": "request_9",
    "numberOfRequests": {
        "total": 1,
        "ok": 1,
        "ko": 0
    },
    "minResponseTime": {
        "total": 1256,
        "ok": 1256,
        "ko": 0
    },
    "maxResponseTime": {
        "total": 1256,
        "ok": 1256,
        "ko": 0
    },
    "meanResponseTime": {
        "total": 1256,
        "ok": 1256,
        "ko": 0
    },
    "standardDeviation": {
        "total": 0,
        "ok": 0,
        "ko": 0
    },
    "percentiles1": {
        "total": 1256,
        "ok": 1256,
        "ko": 0
    },
    "percentiles2": {
        "total": 1256,
        "ok": 1256,
        "ko": 0
    },
    "percentiles3": {
        "total": 1256,
        "ok": 1256,
        "ko": 0
    },
    "percentiles4": {
        "total": 1256,
        "ok": 1256,
        "ko": 0
    },
    "group1": {
    "name": "t < 800 ms",
    "count": 0,
    "percentage": 0
},
    "group2": {
    "name": "800 ms < t < 1200 ms",
    "count": 0,
    "percentage": 0
},
    "group3": {
    "name": "t > 1200 ms",
    "count": 1,
    "percentage": 100
},
    "group4": {
    "name": "failed",
    "count": 0,
    "percentage": 0
},
    "meanNumberOfRequestsPerSecond": {
        "total": 0.125,
        "ok": 0.125,
        "ko": 0
    }
}
    },"req_request-8-ef0c8": {
        "type": "REQUEST",
        "name": "request_8",
"path": "PetStore_S01_PetSearch_101_LaunchURL / request_8",
"pathFormatted": "req_petstore-s01-pe-17756",
"stats": {
    "name": "request_8",
    "numberOfRequests": {
        "total": 1,
        "ok": 1,
        "ko": 0
    },
    "minResponseTime": {
        "total": 1023,
        "ok": 1023,
        "ko": 0
    },
    "maxResponseTime": {
        "total": 1023,
        "ok": 1023,
        "ko": 0
    },
    "meanResponseTime": {
        "total": 1023,
        "ok": 1023,
        "ko": 0
    },
    "standardDeviation": {
        "total": 0,
        "ok": 0,
        "ko": 0
    },
    "percentiles1": {
        "total": 1023,
        "ok": 1023,
        "ko": 0
    },
    "percentiles2": {
        "total": 1023,
        "ok": 1023,
        "ko": 0
    },
    "percentiles3": {
        "total": 1023,
        "ok": 1023,
        "ko": 0
    },
    "percentiles4": {
        "total": 1023,
        "ok": 1023,
        "ko": 0
    },
    "group1": {
    "name": "t < 800 ms",
    "count": 0,
    "percentage": 0
},
    "group2": {
    "name": "800 ms < t < 1200 ms",
    "count": 1,
    "percentage": 100
},
    "group3": {
    "name": "t > 1200 ms",
    "count": 0,
    "percentage": 0
},
    "group4": {
    "name": "failed",
    "count": 0,
    "percentage": 0
},
    "meanNumberOfRequestsPerSecond": {
        "total": 0.125,
        "ok": 0.125,
        "ko": 0
    }
}
    },"req_request-4-e7d1b": {
        "type": "REQUEST",
        "name": "request_4",
"path": "PetStore_S01_PetSearch_101_LaunchURL / request_4",
"pathFormatted": "req_petstore-s01-pe-7b51d",
"stats": {
    "name": "request_4",
    "numberOfRequests": {
        "total": 1,
        "ok": 1,
        "ko": 0
    },
    "minResponseTime": {
        "total": 758,
        "ok": 758,
        "ko": 0
    },
    "maxResponseTime": {
        "total": 758,
        "ok": 758,
        "ko": 0
    },
    "meanResponseTime": {
        "total": 758,
        "ok": 758,
        "ko": 0
    },
    "standardDeviation": {
        "total": 0,
        "ok": 0,
        "ko": 0
    },
    "percentiles1": {
        "total": 758,
        "ok": 758,
        "ko": 0
    },
    "percentiles2": {
        "total": 758,
        "ok": 758,
        "ko": 0
    },
    "percentiles3": {
        "total": 758,
        "ok": 758,
        "ko": 0
    },
    "percentiles4": {
        "total": 758,
        "ok": 758,
        "ko": 0
    },
    "group1": {
    "name": "t < 800 ms",
    "count": 1,
    "percentage": 100
},
    "group2": {
    "name": "800 ms < t < 1200 ms",
    "count": 0,
    "percentage": 0
},
    "group3": {
    "name": "t > 1200 ms",
    "count": 0,
    "percentage": 0
},
    "group4": {
    "name": "failed",
    "count": 0,
    "percentage": 0
},
    "meanNumberOfRequestsPerSecond": {
        "total": 0.125,
        "ok": 0.125,
        "ko": 0
    }
}
    },"req_request-3-d0973": {
        "type": "REQUEST",
        "name": "request_3",
"path": "PetStore_S01_PetSearch_101_LaunchURL / request_3",
"pathFormatted": "req_petstore-s01-pe-7487a",
"stats": {
    "name": "request_3",
    "numberOfRequests": {
        "total": 1,
        "ok": 1,
        "ko": 0
    },
    "minResponseTime": {
        "total": 533,
        "ok": 533,
        "ko": 0
    },
    "maxResponseTime": {
        "total": 533,
        "ok": 533,
        "ko": 0
    },
    "meanResponseTime": {
        "total": 533,
        "ok": 533,
        "ko": 0
    },
    "standardDeviation": {
        "total": 0,
        "ok": 0,
        "ko": 0
    },
    "percentiles1": {
        "total": 533,
        "ok": 533,
        "ko": 0
    },
    "percentiles2": {
        "total": 533,
        "ok": 533,
        "ko": 0
    },
    "percentiles3": {
        "total": 533,
        "ok": 533,
        "ko": 0
    },
    "percentiles4": {
        "total": 533,
        "ok": 533,
        "ko": 0
    },
    "group1": {
    "name": "t < 800 ms",
    "count": 1,
    "percentage": 100
},
    "group2": {
    "name": "800 ms < t < 1200 ms",
    "count": 0,
    "percentage": 0
},
    "group3": {
    "name": "t > 1200 ms",
    "count": 0,
    "percentage": 0
},
    "group4": {
    "name": "failed",
    "count": 0,
    "percentage": 0
},
    "meanNumberOfRequestsPerSecond": {
        "total": 0.125,
        "ok": 0.125,
        "ko": 0
    }
}
    },"req_request-2-93baf": {
        "type": "REQUEST",
        "name": "request_2",
"path": "PetStore_S01_PetSearch_101_LaunchURL / request_2",
"pathFormatted": "req_petstore-s01-pe-4895a",
"stats": {
    "name": "request_2",
    "numberOfRequests": {
        "total": 1,
        "ok": 1,
        "ko": 0
    },
    "minResponseTime": {
        "total": 878,
        "ok": 878,
        "ko": 0
    },
    "maxResponseTime": {
        "total": 878,
        "ok": 878,
        "ko": 0
    },
    "meanResponseTime": {
        "total": 878,
        "ok": 878,
        "ko": 0
    },
    "standardDeviation": {
        "total": 0,
        "ok": 0,
        "ko": 0
    },
    "percentiles1": {
        "total": 878,
        "ok": 878,
        "ko": 0
    },
    "percentiles2": {
        "total": 878,
        "ok": 878,
        "ko": 0
    },
    "percentiles3": {
        "total": 878,
        "ok": 878,
        "ko": 0
    },
    "percentiles4": {
        "total": 878,
        "ok": 878,
        "ko": 0
    },
    "group1": {
    "name": "t < 800 ms",
    "count": 0,
    "percentage": 0
},
    "group2": {
    "name": "800 ms < t < 1200 ms",
    "count": 1,
    "percentage": 100
},
    "group3": {
    "name": "t > 1200 ms",
    "count": 0,
    "percentage": 0
},
    "group4": {
    "name": "failed",
    "count": 0,
    "percentage": 0
},
    "meanNumberOfRequestsPerSecond": {
        "total": 0.125,
        "ok": 0.125,
        "ko": 0
    }
}
    },"req_request-11-f11e8": {
        "type": "REQUEST",
        "name": "request_11",
"path": "PetStore_S01_PetSearch_101_LaunchURL / request_11",
"pathFormatted": "req_petstore-s01-pe-f7a27",
"stats": {
    "name": "request_11",
    "numberOfRequests": {
        "total": 1,
        "ok": 1,
        "ko": 0
    },
    "minResponseTime": {
        "total": 751,
        "ok": 751,
        "ko": 0
    },
    "maxResponseTime": {
        "total": 751,
        "ok": 751,
        "ko": 0
    },
    "meanResponseTime": {
        "total": 751,
        "ok": 751,
        "ko": 0
    },
    "standardDeviation": {
        "total": 0,
        "ok": 0,
        "ko": 0
    },
    "percentiles1": {
        "total": 751,
        "ok": 751,
        "ko": 0
    },
    "percentiles2": {
        "total": 751,
        "ok": 751,
        "ko": 0
    },
    "percentiles3": {
        "total": 751,
        "ok": 751,
        "ko": 0
    },
    "percentiles4": {
        "total": 751,
        "ok": 751,
        "ko": 0
    },
    "group1": {
    "name": "t < 800 ms",
    "count": 1,
    "percentage": 100
},
    "group2": {
    "name": "800 ms < t < 1200 ms",
    "count": 0,
    "percentage": 0
},
    "group3": {
    "name": "t > 1200 ms",
    "count": 0,
    "percentage": 0
},
    "group4": {
    "name": "failed",
    "count": 0,
    "percentage": 0
},
    "meanNumberOfRequestsPerSecond": {
        "total": 0.125,
        "ok": 0.125,
        "ko": 0
    }
}
    },"req_request-7-f222f": {
        "type": "REQUEST",
        "name": "request_7",
"path": "PetStore_S01_PetSearch_101_LaunchURL / request_7",
"pathFormatted": "req_petstore-s01-pe-ccdf2",
"stats": {
    "name": "request_7",
    "numberOfRequests": {
        "total": 1,
        "ok": 1,
        "ko": 0
    },
    "minResponseTime": {
        "total": 1012,
        "ok": 1012,
        "ko": 0
    },
    "maxResponseTime": {
        "total": 1012,
        "ok": 1012,
        "ko": 0
    },
    "meanResponseTime": {
        "total": 1012,
        "ok": 1012,
        "ko": 0
    },
    "standardDeviation": {
        "total": 0,
        "ok": 0,
        "ko": 0
    },
    "percentiles1": {
        "total": 1012,
        "ok": 1012,
        "ko": 0
    },
    "percentiles2": {
        "total": 1012,
        "ok": 1012,
        "ko": 0
    },
    "percentiles3": {
        "total": 1012,
        "ok": 1012,
        "ko": 0
    },
    "percentiles4": {
        "total": 1012,
        "ok": 1012,
        "ko": 0
    },
    "group1": {
    "name": "t < 800 ms",
    "count": 0,
    "percentage": 0
},
    "group2": {
    "name": "800 ms < t < 1200 ms",
    "count": 1,
    "percentage": 100
},
    "group3": {
    "name": "t > 1200 ms",
    "count": 0,
    "percentage": 0
},
    "group4": {
    "name": "failed",
    "count": 0,
    "percentage": 0
},
    "meanNumberOfRequestsPerSecond": {
        "total": 0.125,
        "ok": 0.125,
        "ko": 0
    }
}
    },"req_request-12-61da2": {
        "type": "REQUEST",
        "name": "request_12",
"path": "PetStore_S01_PetSearch_101_LaunchURL / request_12",
"pathFormatted": "req_petstore-s01-pe-764fa",
"stats": {
    "name": "request_12",
    "numberOfRequests": {
        "total": 1,
        "ok": 1,
        "ko": 0
    },
    "minResponseTime": {
        "total": 1016,
        "ok": 1016,
        "ko": 0
    },
    "maxResponseTime": {
        "total": 1016,
        "ok": 1016,
        "ko": 0
    },
    "meanResponseTime": {
        "total": 1016,
        "ok": 1016,
        "ko": 0
    },
    "standardDeviation": {
        "total": 0,
        "ok": 0,
        "ko": 0
    },
    "percentiles1": {
        "total": 1016,
        "ok": 1016,
        "ko": 0
    },
    "percentiles2": {
        "total": 1016,
        "ok": 1016,
        "ko": 0
    },
    "percentiles3": {
        "total": 1016,
        "ok": 1016,
        "ko": 0
    },
    "percentiles4": {
        "total": 1016,
        "ok": 1016,
        "ko": 0
    },
    "group1": {
    "name": "t < 800 ms",
    "count": 0,
    "percentage": 0
},
    "group2": {
    "name": "800 ms < t < 1200 ms",
    "count": 1,
    "percentage": 100
},
    "group3": {
    "name": "t > 1200 ms",
    "count": 0,
    "percentage": 0
},
    "group4": {
    "name": "failed",
    "count": 0,
    "percentage": 0
},
    "meanNumberOfRequestsPerSecond": {
        "total": 0.125,
        "ok": 0.125,
        "ko": 0
    }
}
    },"req_request-14-a0e30": {
        "type": "REQUEST",
        "name": "request_14",
"path": "PetStore_S01_PetSearch_101_LaunchURL / request_14",
"pathFormatted": "req_petstore-s01-pe-4c912",
"stats": {
    "name": "request_14",
    "numberOfRequests": {
        "total": 1,
        "ok": 1,
        "ko": 0
    },
    "minResponseTime": {
        "total": 741,
        "ok": 741,
        "ko": 0
    },
    "maxResponseTime": {
        "total": 741,
        "ok": 741,
        "ko": 0
    },
    "meanResponseTime": {
        "total": 741,
        "ok": 741,
        "ko": 0
    },
    "standardDeviation": {
        "total": 0,
        "ok": 0,
        "ko": 0
    },
    "percentiles1": {
        "total": 741,
        "ok": 741,
        "ko": 0
    },
    "percentiles2": {
        "total": 741,
        "ok": 741,
        "ko": 0
    },
    "percentiles3": {
        "total": 741,
        "ok": 741,
        "ko": 0
    },
    "percentiles4": {
        "total": 741,
        "ok": 741,
        "ko": 0
    },
    "group1": {
    "name": "t < 800 ms",
    "count": 1,
    "percentage": 100
},
    "group2": {
    "name": "800 ms < t < 1200 ms",
    "count": 0,
    "percentage": 0
},
    "group3": {
    "name": "t > 1200 ms",
    "count": 0,
    "percentage": 0
},
    "group4": {
    "name": "failed",
    "count": 0,
    "percentage": 0
},
    "meanNumberOfRequestsPerSecond": {
        "total": 0.125,
        "ok": 0.125,
        "ko": 0
    }
}
    },"req_request-15-56eac": {
        "type": "REQUEST",
        "name": "request_15",
"path": "PetStore_S01_PetSearch_101_LaunchURL / request_15",
"pathFormatted": "req_petstore-s01-pe-538c0",
"stats": {
    "name": "request_15",
    "numberOfRequests": {
        "total": 1,
        "ok": 1,
        "ko": 0
    },
    "minResponseTime": {
        "total": 742,
        "ok": 742,
        "ko": 0
    },
    "maxResponseTime": {
        "total": 742,
        "ok": 742,
        "ko": 0
    },
    "meanResponseTime": {
        "total": 742,
        "ok": 742,
        "ko": 0
    },
    "standardDeviation": {
        "total": 0,
        "ok": 0,
        "ko": 0
    },
    "percentiles1": {
        "total": 742,
        "ok": 742,
        "ko": 0
    },
    "percentiles2": {
        "total": 742,
        "ok": 742,
        "ko": 0
    },
    "percentiles3": {
        "total": 742,
        "ok": 742,
        "ko": 0
    },
    "percentiles4": {
        "total": 742,
        "ok": 742,
        "ko": 0
    },
    "group1": {
    "name": "t < 800 ms",
    "count": 1,
    "percentage": 100
},
    "group2": {
    "name": "800 ms < t < 1200 ms",
    "count": 0,
    "percentage": 0
},
    "group3": {
    "name": "t > 1200 ms",
    "count": 0,
    "percentage": 0
},
    "group4": {
    "name": "failed",
    "count": 0,
    "percentage": 0
},
    "meanNumberOfRequestsPerSecond": {
        "total": 0.125,
        "ok": 0.125,
        "ko": 0
    }
}
    }
}

     },"group_petstore-s01-pe-4b0dc": {
          "type": "GROUP",
"name": "PetStore_S01_PetSearch_102_Login",
"path": "PetStore_S01_PetSearch_102_Login",
"pathFormatted": "group_petstore-s01-pe-4b0dc",
"stats": {
    "name": "PetStore_S01_PetSearch_102_Login",
    "numberOfRequests": {
        "total": 1,
        "ok": 0,
        "ko": 1
    },
    "minResponseTime": {
        "total": 922,
        "ok": 0,
        "ko": 922
    },
    "maxResponseTime": {
        "total": 922,
        "ok": 0,
        "ko": 922
    },
    "meanResponseTime": {
        "total": 922,
        "ok": 0,
        "ko": 922
    },
    "standardDeviation": {
        "total": 0,
        "ok": 0,
        "ko": 0
    },
    "percentiles1": {
        "total": 922,
        "ok": 0,
        "ko": 922
    },
    "percentiles2": {
        "total": 922,
        "ok": 0,
        "ko": 922
    },
    "percentiles3": {
        "total": 922,
        "ok": 0,
        "ko": 922
    },
    "percentiles4": {
        "total": 922,
        "ok": 0,
        "ko": 922
    },
    "group1": {
    "name": "t < 800 ms",
    "count": 0,
    "percentage": 0
},
    "group2": {
    "name": "800 ms < t < 1200 ms",
    "count": 0,
    "percentage": 0
},
    "group3": {
    "name": "t > 1200 ms",
    "count": 0,
    "percentage": 0
},
    "group4": {
    "name": "failed",
    "count": 1,
    "percentage": 100
},
    "meanNumberOfRequestsPerSecond": {
        "total": 0.125,
        "ok": 0,
        "ko": 0.125
    }
},
"contents": {
"req_request-16-24733": {
        "type": "REQUEST",
        "name": "request_16",
"path": "PetStore_S01_PetSearch_102_Login / request_16",
"pathFormatted": "req_petstore-s01-pe-c24af",
"stats": {
    "name": "request_16",
    "numberOfRequests": {
        "total": 1,
        "ok": 1,
        "ko": 0
    },
    "minResponseTime": {
        "total": 922,
        "ok": 922,
        "ko": 0
    },
    "maxResponseTime": {
        "total": 922,
        "ok": 922,
        "ko": 0
    },
    "meanResponseTime": {
        "total": 922,
        "ok": 922,
        "ko": 0
    },
    "standardDeviation": {
        "total": 0,
        "ok": 0,
        "ko": 0
    },
    "percentiles1": {
        "total": 922,
        "ok": 922,
        "ko": 0
    },
    "percentiles2": {
        "total": 922,
        "ok": 922,
        "ko": 0
    },
    "percentiles3": {
        "total": 922,
        "ok": 922,
        "ko": 0
    },
    "percentiles4": {
        "total": 922,
        "ok": 922,
        "ko": 0
    },
    "group1": {
    "name": "t < 800 ms",
    "count": 0,
    "percentage": 0
},
    "group2": {
    "name": "800 ms < t < 1200 ms",
    "count": 1,
    "percentage": 100
},
    "group3": {
    "name": "t > 1200 ms",
    "count": 0,
    "percentage": 0
},
    "group4": {
    "name": "failed",
    "count": 0,
    "percentage": 0
},
    "meanNumberOfRequestsPerSecond": {
        "total": 0.125,
        "ok": 0.125,
        "ko": 0
    }
}
    }
}

     },"group_petstore-s01-pe-9436f": {
          "type": "GROUP",
"name": "PetStore_S01_PetSearch_103_SearchGoldfish",
"path": "PetStore_S01_PetSearch_103_SearchGoldfish",
"pathFormatted": "group_petstore-s01-pe-9436f",
"stats": {
    "name": "PetStore_S01_PetSearch_103_SearchGoldfish",
    "numberOfRequests": {
        "total": 1,
        "ok": 0,
        "ko": 1
    },
    "minResponseTime": {
        "total": 913,
        "ok": 0,
        "ko": 913
    },
    "maxResponseTime": {
        "total": 913,
        "ok": 0,
        "ko": 913
    },
    "meanResponseTime": {
        "total": 913,
        "ok": 0,
        "ko": 913
    },
    "standardDeviation": {
        "total": 0,
        "ok": 0,
        "ko": 0
    },
    "percentiles1": {
        "total": 913,
        "ok": 0,
        "ko": 913
    },
    "percentiles2": {
        "total": 913,
        "ok": 0,
        "ko": 913
    },
    "percentiles3": {
        "total": 913,
        "ok": 0,
        "ko": 913
    },
    "percentiles4": {
        "total": 913,
        "ok": 0,
        "ko": 913
    },
    "group1": {
    "name": "t < 800 ms",
    "count": 0,
    "percentage": 0
},
    "group2": {
    "name": "800 ms < t < 1200 ms",
    "count": 0,
    "percentage": 0
},
    "group3": {
    "name": "t > 1200 ms",
    "count": 0,
    "percentage": 0
},
    "group4": {
    "name": "failed",
    "count": 1,
    "percentage": 100
},
    "meanNumberOfRequestsPerSecond": {
        "total": 0.125,
        "ok": 0,
        "ko": 0.125
    }
},
"contents": {
"req_request-32-84a21": {
        "type": "REQUEST",
        "name": "request_32",
"path": "PetStore_S01_PetSearch_103_SearchGoldfish / request_32",
"pathFormatted": "req_petstore-s01-pe-7b360",
"stats": {
    "name": "request_32",
    "numberOfRequests": {
        "total": 1,
        "ok": 0,
        "ko": 1
    },
    "minResponseTime": {
        "total": 913,
        "ok": 0,
        "ko": 913
    },
    "maxResponseTime": {
        "total": 913,
        "ok": 0,
        "ko": 913
    },
    "meanResponseTime": {
        "total": 913,
        "ok": 0,
        "ko": 913
    },
    "standardDeviation": {
        "total": 0,
        "ok": 0,
        "ko": 0
    },
    "percentiles1": {
        "total": 913,
        "ok": 0,
        "ko": 913
    },
    "percentiles2": {
        "total": 913,
        "ok": 0,
        "ko": 913
    },
    "percentiles3": {
        "total": 913,
        "ok": 0,
        "ko": 913
    },
    "percentiles4": {
        "total": 913,
        "ok": 0,
        "ko": 913
    },
    "group1": {
    "name": "t < 800 ms",
    "count": 0,
    "percentage": 0
},
    "group2": {
    "name": "800 ms < t < 1200 ms",
    "count": 0,
    "percentage": 0
},
    "group3": {
    "name": "t > 1200 ms",
    "count": 0,
    "percentage": 0
},
    "group4": {
    "name": "failed",
    "count": 1,
    "percentage": 100
},
    "meanNumberOfRequestsPerSecond": {
        "total": 0.125,
        "ok": 0,
        "ko": 0.125
    }
}
    }
}

     },"group_petstore-s01-pe-2f90a": {
          "type": "GROUP",
"name": "PetStore_S01_PetSearch_104_SelectFemalepuppy",
"path": "PetStore_S01_PetSearch_104_SelectFemalepuppy",
"pathFormatted": "group_petstore-s01-pe-2f90a",
"stats": {
    "name": "PetStore_S01_PetSearch_104_SelectFemalepuppy",
    "numberOfRequests": {
        "total": 1,
        "ok": 1,
        "ko": 0
    },
    "minResponseTime": {
        "total": 586,
        "ok": 586,
        "ko": 0
    },
    "maxResponseTime": {
        "total": 586,
        "ok": 586,
        "ko": 0
    },
    "meanResponseTime": {
        "total": 586,
        "ok": 586,
        "ko": 0
    },
    "standardDeviation": {
        "total": 0,
        "ok": 0,
        "ko": 0
    },
    "percentiles1": {
        "total": 586,
        "ok": 586,
        "ko": 0
    },
    "percentiles2": {
        "total": 586,
        "ok": 586,
        "ko": 0
    },
    "percentiles3": {
        "total": 586,
        "ok": 586,
        "ko": 0
    },
    "percentiles4": {
        "total": 586,
        "ok": 586,
        "ko": 0
    },
    "group1": {
    "name": "t < 800 ms",
    "count": 1,
    "percentage": 100
},
    "group2": {
    "name": "800 ms < t < 1200 ms",
    "count": 0,
    "percentage": 0
},
    "group3": {
    "name": "t > 1200 ms",
    "count": 0,
    "percentage": 0
},
    "group4": {
    "name": "failed",
    "count": 0,
    "percentage": 0
},
    "meanNumberOfRequestsPerSecond": {
        "total": 0.125,
        "ok": 0.125,
        "ko": 0
    }
},
"contents": {
"req_request-37-6b2c3": {
        "type": "REQUEST",
        "name": "request_37",
"path": "PetStore_S01_PetSearch_104_SelectFemalepuppy / request_37",
"pathFormatted": "req_petstore-s01-pe-378b4",
"stats": {
    "name": "request_37",
    "numberOfRequests": {
        "total": 1,
        "ok": 1,
        "ko": 0
    },
    "minResponseTime": {
        "total": 293,
        "ok": 293,
        "ko": 0
    },
    "maxResponseTime": {
        "total": 293,
        "ok": 293,
        "ko": 0
    },
    "meanResponseTime": {
        "total": 293,
        "ok": 293,
        "ko": 0
    },
    "standardDeviation": {
        "total": 0,
        "ok": 0,
        "ko": 0
    },
    "percentiles1": {
        "total": 293,
        "ok": 293,
        "ko": 0
    },
    "percentiles2": {
        "total": 293,
        "ok": 293,
        "ko": 0
    },
    "percentiles3": {
        "total": 293,
        "ok": 293,
        "ko": 0
    },
    "percentiles4": {
        "total": 293,
        "ok": 293,
        "ko": 0
    },
    "group1": {
    "name": "t < 800 ms",
    "count": 1,
    "percentage": 100
},
    "group2": {
    "name": "800 ms < t < 1200 ms",
    "count": 0,
    "percentage": 0
},
    "group3": {
    "name": "t > 1200 ms",
    "count": 0,
    "percentage": 0
},
    "group4": {
    "name": "failed",
    "count": 0,
    "percentage": 0
},
    "meanNumberOfRequestsPerSecond": {
        "total": 0.125,
        "ok": 0.125,
        "ko": 0
    }
}
    },"req_request-39-bb0c9": {
        "type": "REQUEST",
        "name": "request_39",
"path": "PetStore_S01_PetSearch_104_SelectFemalepuppy / request_39",
"pathFormatted": "req_petstore-s01-pe-237eb",
"stats": {
    "name": "request_39",
    "numberOfRequests": {
        "total": 1,
        "ok": 1,
        "ko": 0
    },
    "minResponseTime": {
        "total": 287,
        "ok": 287,
        "ko": 0
    },
    "maxResponseTime": {
        "total": 287,
        "ok": 287,
        "ko": 0
    },
    "meanResponseTime": {
        "total": 287,
        "ok": 287,
        "ko": 0
    },
    "standardDeviation": {
        "total": 0,
        "ok": 0,
        "ko": 0
    },
    "percentiles1": {
        "total": 287,
        "ok": 287,
        "ko": 0
    },
    "percentiles2": {
        "total": 287,
        "ok": 287,
        "ko": 0
    },
    "percentiles3": {
        "total": 287,
        "ok": 287,
        "ko": 0
    },
    "percentiles4": {
        "total": 287,
        "ok": 287,
        "ko": 0
    },
    "group1": {
    "name": "t < 800 ms",
    "count": 1,
    "percentage": 100
},
    "group2": {
    "name": "800 ms < t < 1200 ms",
    "count": 0,
    "percentage": 0
},
    "group3": {
    "name": "t > 1200 ms",
    "count": 0,
    "percentage": 0
},
    "group4": {
    "name": "failed",
    "count": 0,
    "percentage": 0
},
    "meanNumberOfRequestsPerSecond": {
        "total": 0.125,
        "ok": 0.125,
        "ko": 0
    }
}
    },"req_request-38-ab13e": {
        "type": "REQUEST",
        "name": "request_38",
"path": "PetStore_S01_PetSearch_104_SelectFemalepuppy / request_38",
"pathFormatted": "req_petstore-s01-pe-a26c0",
"stats": {
    "name": "request_38",
    "numberOfRequests": {
        "total": 1,
        "ok": 1,
        "ko": 0
    },
    "minResponseTime": {
        "total": 248,
        "ok": 248,
        "ko": 0
    },
    "maxResponseTime": {
        "total": 248,
        "ok": 248,
        "ko": 0
    },
    "meanResponseTime": {
        "total": 248,
        "ok": 248,
        "ko": 0
    },
    "standardDeviation": {
        "total": 0,
        "ok": 0,
        "ko": 0
    },
    "percentiles1": {
        "total": 248,
        "ok": 248,
        "ko": 0
    },
    "percentiles2": {
        "total": 248,
        "ok": 248,
        "ko": 0
    },
    "percentiles3": {
        "total": 248,
        "ok": 248,
        "ko": 0
    },
    "percentiles4": {
        "total": 248,
        "ok": 248,
        "ko": 0
    },
    "group1": {
    "name": "t < 800 ms",
    "count": 1,
    "percentage": 100
},
    "group2": {
    "name": "800 ms < t < 1200 ms",
    "count": 0,
    "percentage": 0
},
    "group3": {
    "name": "t > 1200 ms",
    "count": 0,
    "percentage": 0
},
    "group4": {
    "name": "failed",
    "count": 0,
    "percentage": 0
},
    "meanNumberOfRequestsPerSecond": {
        "total": 0.125,
        "ok": 0.125,
        "ko": 0
    }
}
    },"req_request-40-3bad7": {
        "type": "REQUEST",
        "name": "request_40",
"path": "PetStore_S01_PetSearch_104_SelectFemalepuppy / request_40",
"pathFormatted": "req_petstore-s01-pe-ec105",
"stats": {
    "name": "request_40",
    "numberOfRequests": {
        "total": 1,
        "ok": 1,
        "ko": 0
    },
    "minResponseTime": {
        "total": 277,
        "ok": 277,
        "ko": 0
    },
    "maxResponseTime": {
        "total": 277,
        "ok": 277,
        "ko": 0
    },
    "meanResponseTime": {
        "total": 277,
        "ok": 277,
        "ko": 0
    },
    "standardDeviation": {
        "total": 0,
        "ok": 0,
        "ko": 0
    },
    "percentiles1": {
        "total": 277,
        "ok": 277,
        "ko": 0
    },
    "percentiles2": {
        "total": 277,
        "ok": 277,
        "ko": 0
    },
    "percentiles3": {
        "total": 277,
        "ok": 277,
        "ko": 0
    },
    "percentiles4": {
        "total": 277,
        "ok": 277,
        "ko": 0
    },
    "group1": {
    "name": "t < 800 ms",
    "count": 1,
    "percentage": 100
},
    "group2": {
    "name": "800 ms < t < 1200 ms",
    "count": 0,
    "percentage": 0
},
    "group3": {
    "name": "t > 1200 ms",
    "count": 0,
    "percentage": 0
},
    "group4": {
    "name": "failed",
    "count": 0,
    "percentage": 0
},
    "meanNumberOfRequestsPerSecond": {
        "total": 0.125,
        "ok": 0.125,
        "ko": 0
    }
}
    }
}

     },"group_petstore-s01-pe-594d2": {
          "type": "GROUP",
"name": "PetStore_S01_PetSearch_105_AddToCart",
"path": "PetStore_S01_PetSearch_105_AddToCart",
"pathFormatted": "group_petstore-s01-pe-594d2",
"stats": {
    "name": "PetStore_S01_PetSearch_105_AddToCart",
    "numberOfRequests": {
        "total": 1,
        "ok": 0,
        "ko": 1
    },
    "minResponseTime": {
        "total": 987,
        "ok": 0,
        "ko": 987
    },
    "maxResponseTime": {
        "total": 987,
        "ok": 0,
        "ko": 987
    },
    "meanResponseTime": {
        "total": 987,
        "ok": 0,
        "ko": 987
    },
    "standardDeviation": {
        "total": 0,
        "ok": 0,
        "ko": 0
    },
    "percentiles1": {
        "total": 987,
        "ok": 0,
        "ko": 987
    },
    "percentiles2": {
        "total": 987,
        "ok": 0,
        "ko": 987
    },
    "percentiles3": {
        "total": 987,
        "ok": 0,
        "ko": 987
    },
    "percentiles4": {
        "total": 987,
        "ok": 0,
        "ko": 987
    },
    "group1": {
    "name": "t < 800 ms",
    "count": 0,
    "percentage": 0
},
    "group2": {
    "name": "800 ms < t < 1200 ms",
    "count": 0,
    "percentage": 0
},
    "group3": {
    "name": "t > 1200 ms",
    "count": 0,
    "percentage": 0
},
    "group4": {
    "name": "failed",
    "count": 1,
    "percentage": 100
},
    "meanNumberOfRequestsPerSecond": {
        "total": 0.125,
        "ok": 0,
        "ko": 0.125
    }
},
"contents": {
"req_request-41-12d9b": {
        "type": "REQUEST",
        "name": "request_41",
"path": "PetStore_S01_PetSearch_105_AddToCart / request_41",
"pathFormatted": "req_petstore-s01-pe-ac481",
"stats": {
    "name": "request_41",
    "numberOfRequests": {
        "total": 1,
        "ok": 0,
        "ko": 1
    },
    "minResponseTime": {
        "total": 987,
        "ok": 0,
        "ko": 987
    },
    "maxResponseTime": {
        "total": 987,
        "ok": 0,
        "ko": 987
    },
    "meanResponseTime": {
        "total": 987,
        "ok": 0,
        "ko": 987
    },
    "standardDeviation": {
        "total": 0,
        "ok": 0,
        "ko": 0
    },
    "percentiles1": {
        "total": 987,
        "ok": 0,
        "ko": 987
    },
    "percentiles2": {
        "total": 987,
        "ok": 0,
        "ko": 987
    },
    "percentiles3": {
        "total": 987,
        "ok": 0,
        "ko": 987
    },
    "percentiles4": {
        "total": 987,
        "ok": 0,
        "ko": 987
    },
    "group1": {
    "name": "t < 800 ms",
    "count": 0,
    "percentage": 0
},
    "group2": {
    "name": "800 ms < t < 1200 ms",
    "count": 0,
    "percentage": 0
},
    "group3": {
    "name": "t > 1200 ms",
    "count": 0,
    "percentage": 0
},
    "group4": {
    "name": "failed",
    "count": 1,
    "percentage": 100
},
    "meanNumberOfRequestsPerSecond": {
        "total": 0.125,
        "ok": 0,
        "ko": 0.125
    }
}
    }
}

     },"group_petstore-s01-pe-43fec": {
          "type": "GROUP",
"name": "PetStore_S01_PetSearch_106_Logout",
"path": "PetStore_S01_PetSearch_106_Logout",
"pathFormatted": "group_petstore-s01-pe-43fec",
"stats": {
    "name": "PetStore_S01_PetSearch_106_Logout",
    "numberOfRequests": {
        "total": 1,
        "ok": 0,
        "ko": 1
    },
    "minResponseTime": {
        "total": 757,
        "ok": 0,
        "ko": 757
    },
    "maxResponseTime": {
        "total": 757,
        "ok": 0,
        "ko": 757
    },
    "meanResponseTime": {
        "total": 757,
        "ok": 0,
        "ko": 757
    },
    "standardDeviation": {
        "total": 0,
        "ok": 0,
        "ko": 0
    },
    "percentiles1": {
        "total": 757,
        "ok": 0,
        "ko": 757
    },
    "percentiles2": {
        "total": 757,
        "ok": 0,
        "ko": 757
    },
    "percentiles3": {
        "total": 757,
        "ok": 0,
        "ko": 757
    },
    "percentiles4": {
        "total": 757,
        "ok": 0,
        "ko": 757
    },
    "group1": {
    "name": "t < 800 ms",
    "count": 0,
    "percentage": 0
},
    "group2": {
    "name": "800 ms < t < 1200 ms",
    "count": 0,
    "percentage": 0
},
    "group3": {
    "name": "t > 1200 ms",
    "count": 0,
    "percentage": 0
},
    "group4": {
    "name": "failed",
    "count": 1,
    "percentage": 100
},
    "meanNumberOfRequestsPerSecond": {
        "total": 0.125,
        "ok": 0,
        "ko": 0.125
    }
},
"contents": {
"req_request-48-b3bc8": {
        "type": "REQUEST",
        "name": "request_48",
"path": "PetStore_S01_PetSearch_106_Logout / request_48",
"pathFormatted": "req_petstore-s01-pe-2a551",
"stats": {
    "name": "request_48",
    "numberOfRequests": {
        "total": 1,
        "ok": 0,
        "ko": 1
    },
    "minResponseTime": {
        "total": 757,
        "ok": 0,
        "ko": 757
    },
    "maxResponseTime": {
        "total": 757,
        "ok": 0,
        "ko": 757
    },
    "meanResponseTime": {
        "total": 757,
        "ok": 0,
        "ko": 757
    },
    "standardDeviation": {
        "total": 0,
        "ok": 0,
        "ko": 0
    },
    "percentiles1": {
        "total": 757,
        "ok": 0,
        "ko": 757
    },
    "percentiles2": {
        "total": 757,
        "ok": 0,
        "ko": 757
    },
    "percentiles3": {
        "total": 757,
        "ok": 0,
        "ko": 757
    },
    "percentiles4": {
        "total": 757,
        "ok": 0,
        "ko": 757
    },
    "group1": {
    "name": "t < 800 ms",
    "count": 0,
    "percentage": 0
},
    "group2": {
    "name": "800 ms < t < 1200 ms",
    "count": 0,
    "percentage": 0
},
    "group3": {
    "name": "t > 1200 ms",
    "count": 0,
    "percentage": 0
},
    "group4": {
    "name": "failed",
    "count": 1,
    "percentage": 100
},
    "meanNumberOfRequestsPerSecond": {
        "total": 0.125,
        "ok": 0,
        "ko": 0.125
    }
}
    }
}

     }
}

}